Metadata-Version: 1.2
Name: imbox
Version: 0.9.7
Summary: Python IMAP for Human beings
Home-page: https://github.com/martinrusev/imbox
Author: Martin Rusev
Author-email: martin@amon.cx
License: MIT
Keywords: email,IMAP,parsing emails
Platform: UNKNOWN
Classifier: Programming Language :: Python
Classifier: Programming Language :: Python :: 3.3
Classifier: Programming Language :: Python :: 3.4
Classifier: Programming Language :: Python :: 3.5
Classifier: Programming Language :: Python :: 3.6
Classifier: Programming Language :: Python :: 3.7
Requires-Python: >=3.3
